infini_retri/__init__.py
infini_retri/chunks.py
infini_retri/main.py
infini_retri/pipline.py
infini_retri/retrieval.py
infini_retri/thoughts.py
infini_retri/thoughts_old.py
infini_retri-0.0.3.dist-info/METADATA
infini_retri-0.0.3.dist-info/WHEEL
infini_retri-0.0.3.dist-info/licenses/LICENSE
infini_retri-0.0.3.dist-info/RECORD
