Metadata-Version: 2.4
Name: infini-retri
Version: 0.0.3
Summary: This package is designed to improve LLMs alility of handling long contexts, which can enhance LLMs to address retrieval task in infinite-length.
Project-URL: Homepage, https://github.com/MrYxJ
Author-email: MrYXJ <yxj2017@gmail.com>
License: MIT License
License-File: LICENSE
Classifier: License :: OSI Approved :: MIT License
Classifier: Operating System :: OS Independent
Classifier: Programming Language :: Python :: 3
Requires-Python: >=3.8
Requires-Dist: transformers>=4.46.3
